gradient_agent/__init__.py
gradient_agent/decorator.py
gradient_agent/_vendor/__init__.py
gradient_agent/_vendor/doctl/__init__.py
gradient_agent/_vendor/doctl/darwin_amd64/__init__.py
gradient_agent/_vendor/doctl/darwin_amd64/doctl
gradient_agent/_vendor/doctl/darwin_arm64/__init__.py
gradient_agent/_vendor/doctl/darwin_arm64/doctl
gradient_agent/_vendor/doctl/linux_amd64/__init__.py
gradient_agent/_vendor/doctl/linux_amd64/doctl
gradient_agent/_vendor/doctl/linux_arm64/__init__.py
gradient_agent/_vendor/doctl/linux_arm64/doctl
gradient_agent/_vendor/doctl/windows_amd64/__init__.py
gradient_agent/_vendor/doctl/windows_amd64/doctl.exe
gradient_agent/cli/__init__.py
gradient_agent/cli/cli.py
gradient_agent/cli/interfaces.py
gradient_agent/cli/services.py
gradient_agent/runtime/__init__.py
gradient_agent/runtime/context.py
gradient_agent/runtime/interfaces.py
gradient_agent/runtime/langgraph_instrumentor.py
gradient_agent/runtime/manager.py
gradient_agent/runtime/tracker.py
gradient_agent-0.2.5.dist-info/METADATA
gradient_agent-0.2.5.dist-info/WHEEL
gradient_agent-0.2.5.dist-info/entry_points.txt
gradient_agent-0.2.5.dist-info/top_level.txt
gradient_agent-0.2.5.dist-info/RECORD
