Metadata-Version: 2.4
Name: gradient-agent
Version: 0.2.5
Summary: Unified Gradient Agent SDK + CLI
Requires-Python: >=3.10
Requires-Dist: fastapi>=0.104.0
Requires-Dist: uvicorn[standard]>=0.24.0
Requires-Dist: pydantic>=2.5.0
Requires-Dist: typing-extensions>=4.8.0
Requires-Dist: typer>=0.12.0
Requires-Dist: PyYAML>=6.0
